Metadata-Version: 1.0
Name: febraban
Version: 0.11.0
Summary: A library to generate files in FEBRABAN formats
Home-page: https://github.com/starkbank/febraban.git
Author: Stark Bank
Author-email: developers@starkbank.com
License: MIT License
Keywords: febraban,cnab,cnab 240,cnab240,febraban240,transfer,billing,bank
Platform: UNKNOWN
